discovered/__init__.py
discovered/discovered.py
discovered/test.py
discovered-0.0.1.dist-info/DESCRIPTION.rst
discovered-0.0.1.dist-info/METADATA
discovered-0.0.1.dist-info/metadata.json
discovered-0.0.1.dist-info/RECORD
discovered-0.0.1.dist-info/top_level.txt
discovered-0.0.1.dist-info/WHEEL
