Metadata-Version: 2.0
Name: discovered
Version: 0.0.1
Summary: Redis-based service discovery for python
Home-page: http://github.com/peterfraedrich/discovered
Author: Peter Fraedrich
Author-email: peter.fraedrich@hexapp.net
License: MIT
Keywords: Redis,service discovery,consensus,discover
Platform: any
Classifier: Development Status :: 2 - Pre-Alpha
Classifier: Intended Audience :: Developers
Classifier: License :: OSI Approved :: MIT License
Classifier: Operating System :: Microsoft :: Windows
Classifier: Operating System :: MacOS
Classifier: Operating System :: POSIX
Classifier: Programming Language :: Python
Classifier: Topic :: Software Development :: Libraries
Classifier: Topic :: Software Development :: Libraries :: Python Modules
Requires-Dist: redis
Requires-Dist: psutil
